hugr-0.15.0.dist-info/METADATA
hugr-0.15.0.dist-info/WHEEL
hugr-0.15.0.dist-info/entry_points.txt
hugr-0.15.0.dist-info/licenses/LICENCE
hugr/__init__.py
hugr/_hugr.abi3.so
hugr/_hugr/__init__.pyi
hugr/_hugr/model.pyi
hugr/_serialization/__init__.py
hugr/_serialization/extension.py
hugr/_serialization/ops.py
hugr/_serialization/serial_hugr.py
hugr/_serialization/testing_hugr.py
hugr/_serialization/tys.py
hugr/build/__init__.py
hugr/build/base.py
hugr/build/cfg.py
hugr/build/cond_loop.py
hugr/build/dfg.py
hugr/build/function.py
hugr/build/tracked_dfg.py
hugr/cli.py
hugr/conftest.py
hugr/envelope.py
hugr/exceptions.py
hugr/ext.py
hugr/hugr/__init__.py
hugr/hugr/base.py
hugr/hugr/node_port.py
hugr/hugr/render.py
hugr/model/__init__.py
hugr/model/export.py
hugr/model/load.py
hugr/ops.py
hugr/package.py
hugr/passes/__init__.py
hugr/passes/_composable_pass.py
hugr/py.typed
hugr/qsystem/__init__.py
hugr/qsystem/result.py
hugr/std/__init__.py
hugr/std/_json_defs/README.md
hugr/std/_json_defs/arithmetic/conversions.json
hugr/std/_json_defs/arithmetic/float.json
hugr/std/_json_defs/arithmetic/float/types.json
hugr/std/_json_defs/arithmetic/int.json
hugr/std/_json_defs/arithmetic/int/types.json
hugr/std/_json_defs/collections/array.json
hugr/std/_json_defs/collections/borrow_arr.json
hugr/std/_json_defs/collections/list.json
hugr/std/_json_defs/collections/static_array.json
hugr/std/_json_defs/logic.json
hugr/std/_json_defs/prelude.json
hugr/std/_json_defs/ptr.json
hugr/std/collections/__init__.py
hugr/std/collections/array.py
hugr/std/collections/borrow_array.py
hugr/std/collections/list.py
hugr/std/collections/static_array.py
hugr/std/float.py
hugr/std/int.py
hugr/std/logic.py
hugr/std/prelude.py
hugr/tys.py
hugr/utils.py
hugr/val.py
hugr-0.15.0.dist-info/RECORD
