Metadata-Version: 2.4
Name: hugr
Version: 0.15.0
Classifier: Environment :: Console
Classifier: Programming Language :: Python :: 3.10
Classifier: Programming Language :: Python :: 3.11
Classifier: Programming Language :: Python :: 3.12
Classifier: Programming Language :: Python :: 3.13
Classifier: Programming Language :: Python :: 3.14
Classifier: License :: OSI Approved :: Apache Software License
Classifier: Operating System :: MacOS :: MacOS X
Classifier: Operating System :: POSIX :: Linux
Classifier: Operating System :: Microsoft :: Windows
Classifier: Intended Audience :: Developers
Classifier: Intended Audience :: Science/Research
Classifier: Topic :: Scientific/Engineering
Requires-Dist: graphviz>=0.20.3
Requires-Dist: pydantic~=2.8
Requires-Dist: pydantic-extra-types~=2.9
Requires-Dist: semver~=3.0
Requires-Dist: typing-extensions~=4.12
Requires-Dist: pyzstd>=0.18,<0.20
Requires-Dist: sphinx>=8.1.3,<9.0.0 ; extra == 'docs'
Requires-Dist: furo ; extra == 'docs'
Requires-Dist: pytket>=1.34.0 ; extra == 'pytket'
Provides-Extra: docs
Provides-Extra: pytket
License-File: LICENCE
Summary: Quantinuum's common representation for quantum programs
Author-email: TKET development team <tket-support@quantinuum.com>
Maintainer-email: TKET development team <tket-support@quantinuum.com>
Requires-Python: >=3.10
Project-URL: homepage, https://github.com/quantinuum/hugr/tree/main/hugr-py
Project-URL: repository, https://github.com/quantinuum/hugr/tree/main/hugr-py
